notifier/__init__.py
notifier/controller.py
providers/__init__.py
providers/email.py
providers/slack.py
utils/__init__.py
utils/exceptions.py
utils/helpers.py
NotificationServices-0.1.dist-info/METADATA
NotificationServices-0.1.dist-info/WHEEL
NotificationServices-0.1.dist-info/top_level.txt
NotificationServices-0.1.dist-info/RECORD
